{"heading":"Mowoni ekri nan enterè Lamanit yo—Nefit ki pa vle nye Kris la yo, pase anba lanmò. Anviwon 401–421 apre Jezikri.","prevAbbr":"ether","nextAbbr":"moro","prevNo":15,"nextNo":2,"chapterTitle":"Mowoni 1","prevTitle":"Etè 15","nextTitle":"Mowoni 2","verses":[{"vNo":1,"txt":"KOUNYEYA, mwen menm Mowoni, lè m te fin fè rezime istwa pèp Jarèd la, m te panse m pa ta p ekri plis, men, m poko peri; e m pa kite Lamanit yo konnen m pou yo pa detwi m."},{"vNo":2,"txt":"Paske gade, lagè yo feròs anpil nan pami yo; e poutèt rayisman yo, yo touye tout Nefit ki pa t vle nye Kris la."},{"vNo":3,"txt":"Epi mwen menm, Mowoni, m p ap nye Kris la; se poutèt sa, m ap pwomennen tout kote pou pwoteksyon lavi pa m."},{"vNo":4,"txt":"Konsa, m ekri kèk lòt bagay, kontrèman avèk jan m te panse a; paske m pa t sipoze m t ap ekri plis; men, m ekri kèk bagay anplis, pou, petèt, yo kapab gen valè pou frè m yo, Lamanit yo, nan jou k ap vini yo, dapre volonte Senyè a."}]}